<beans xmlns="http://www.springframework.org/schema/beans"
	xmlns:xsi="http://www.w3.org/2001/XMLSchema-instance" xmlns:p="http://www.springframework.org/schema/p"
	xmlns:context="http://www.springframework.org/schema/context" xmlns:tx="http://www.springframework.org/schema/tx"
	xmlns:jee="http://www.springframework.org/schema/jee" xmlns:util="http://www.springframework.org/schema/util"
	xmlns:jpa="http://www.springframework.org/schema/data/jpa"
	xmlns:repository="http://www.springframework.org/schema/data/repository"
	xmlns:task="http://www.springframework.org/schema/task"
	xsi:schemaLocation="http://www.springframework.org/schema/jee http://www.springframework.org/schema/jee/spring-jee-3.0.xsd
		http://www.springframework.org/schema/beans http://www.springframework.org/schema/beans/spring-beans-3.0.xsd
		http://www.springframework.org/schema/context http://www.springframework.org/schema/context/spring-context-3.0.xsd
		http://www.springframework.org/schema/task http://www.springframework.org/schema/task/spring-task-3.0.xsd
		http://www.springframework.org/schema/tx http://www.springframework.org/schema/tx/spring-tx-3.0.xsd
		http://www.springframework.org/schema/util http://www.springframework.org/schema/util/spring-util.xsd
		http://www.springframework.org/schema/data/repository http://www.springframework.org/schema/data/repository/spring-repository.xsd
	    http://www.springframework.org/schema/data/jpa http://www.springframework.org/schema/data/jpa/spring-jpa.xsd">

	<bean id="lazyDataSource"
		class="org.springframework.jdbc.datasource.LazyConnectionDataSourceProxy">
		<property name="targetDataSource">
			<ref local="tomcatDataSource" />
		</property>
	</bean>

	<bean id="dataSource"
		class="org.springframework.jdbc.datasource.TransactionAwareDataSourceProxy">
		<constructor-arg ref="lazyDataSource" />
	</bean>

	<bean id="tomcatDataSource" class="org.apache.tomcat.jdbc.pool.DataSource"
		p:driverClassName="${server.database-driver}" p:url="${server.database-url}"
		p:username="${server.database-user}" p:password="${server.database-password}"
		p:defaultAutoCommit="false" p:minIdle="${server.database-minpoolsize}"
		p:maxActive="${server.database-maxpoolsize}" p:maxIdle="${server.database-maxpoolsize}"
		p:initialSize="${server.database-minpoolsize}" p:maxWait="${server.database-blockingtimeout}"
		p:jdbcInterceptors="ConnectionState;StatementFinalizer"
		p:validationQuery="${server.connection-validation-sql}"
		p:validationInterval="30000" p:logAbandoned="true" p:testOnBorrow="true"
		p:defaultTransactionIsolation="2" />

	<bean id="jdbcTemplate" class="org.springframework.jdbc.core.JdbcTemplate">
		<property name="dataSource" ref="dataSource" />
	</bean>

	<bean class="org.springframework.orm.jpa.JpaTransactionManager"
		id="transactionManager">
		<property name="entityManagerFactory" ref="entityManagerFactory" />
		<!--  TODO re-enable SPR-8086 is resolved -->
		<!-- <property name="defaultTimeout" value="${server.transaction.timeout}"/> -->
	</bean>

	<bean
		class="org.springframework.orm.jpa.LocalContainerEntityManagerFactoryBean"
		id="entityManagerFactory" depends-on="neo4jNodeBacking,neo4jRelationshipBacking,liquibase">
		<property name="persistenceUnitName" value="production" />
		<property name="dataSource" ref="dataSource" />
		<property name="persistenceProvider" ref="persistenceProvider"/>
		<property name="persistenceUnitManager">
			<bean
				class="org.springframework.orm.jpa.persistenceunit.DefaultPersistenceUnitManager">
				<property name="defaultDataSource" ref="dataSource" />
			</bean>
		</property>
		<property name="jpaVendorAdapter">
			<bean class="org.springframework.orm.jpa.vendor.HibernateJpaVendorAdapter"/>
		</property>
	</bean>
	
	<bean id="persistenceProvider" class="org.hyperic.hibernate.HibernateConfigHolder" />

	<bean class="org.springframework.orm.jpa.JpaTemplate">
		<constructor-arg ref="entityManagerFactory" />
	</bean>

	<jpa:repositories base-package="org.hyperic.hq.**.data" />
	
	<bean id="exporter" class="org.springframework.jmx.export.MBeanExporter"
		lazy-init="false">
		<property name="beans">
			<map>
				<entry key="hyperic.jmx:type=DataSource,name=tomcat.jdbc"
					value-ref="tomcatDataSource" />
			</map>
		</property>
	</bean>
	
</beans>
